anpa_tools/__init__.py
anpa_tools/anpatools.py
anpa_tools/test_anpatools.py
AnPaFinder-1.2.2.dist-info/LICENSE
AnPaFinder-1.2.2.dist-info/METADATA
AnPaFinder-1.2.2.dist-info/WHEEL
AnPaFinder-1.2.2.dist-info/top_level.txt
AnPaFinder-1.2.2.dist-info/RECORD
