Metadata-Version: 2.1
Name: AnPaFinder
Version: 1.2.2
Summary: A basic package to find anagrams and palindromes.
Home-page: https://github.com/AmryAnn/anpaFinder
Author: Amry Ann
Author-email: AmryAnnCoding@gmail.com
License: UNKNOWN
Platform: UNKNOWN
Classifier: Programming Language :: Python :: 3
Classifier: License :: OSI Approved :: MIT License
Classifier: Operating System :: OS Independent
Requires-Python: >=3.6
License-File: LICENSE
